bzjsons.py
bzjsons-0.0.5.dist-info/LICENSE
bzjsons-0.0.5.dist-info/METADATA
bzjsons-0.0.5.dist-info/WHEEL
bzjsons-0.0.5.dist-info/top_level.txt
bzjsons-0.0.5.dist-info/RECORD
